mochapy/__init__.py
mochapy/mocha.py
mochapy/mocha_client.py
mochapy/mocha_parser.py
mochapy/mocha_request.py
mochapy/mocha_response.py
mochapy-2.0.0.dist-info/LICENSE
mochapy-2.0.0.dist-info/METADATA
mochapy-2.0.0.dist-info/WHEEL
mochapy-2.0.0.dist-info/top_level.txt
mochapy-2.0.0.dist-info/RECORD
